selfeeg/VERSION.txt
selfeeg/__init__.py
selfeeg/augmentation/__init__.py
selfeeg/augmentation/compose.py
selfeeg/augmentation/functional.py
selfeeg/dataloading/__init__.py
selfeeg/dataloading/load.py
selfeeg/losses/__init__.py
selfeeg/losses/losses.py
selfeeg/models/__init__.py
selfeeg/models/encoders.py
selfeeg/models/layers.py
selfeeg/models/zoo.py
selfeeg/ssl/__init__.py
selfeeg/ssl/base.py
selfeeg/ssl/contrastive.py
selfeeg/ssl/generative.py
selfeeg/ssl/predictive.py
selfeeg/utils/__init__.py
selfeeg/utils/utils.py
selfeeg-0.2.1.dist-info/licenses/LICENSE.md
selfeeg-0.2.1.dist-info/METADATA
selfeeg-0.2.1.dist-info/WHEEL
selfeeg-0.2.1.dist-info/top_level.txt
selfeeg-0.2.1.dist-info/RECORD
