Metadata-Version: 2.4
Name: selfeeg
Version: 0.2.1
Summary: Self-Supervised Learning for EEG
Home-page: https://github.com/MedMaxLab/selfEEG
Author: MedMax Team
Author-email: federico.delpup@studenti.unipd.it
License: MIT
Project-URL: Bug Tracker, https://github.com/MedMaxLab/selfEEG/issues
Project-URL: Source Code, https://github.com/MedMaxLab/selfEEG
Project-URL: Documentation, https://selfeeg.readthedocs.io/en/latest/index.html
Keywords: Deep Learning,Self-Supervised Learning,Contrastive Learning,Electroencephalography,EEG
Classifier: Environment :: Console
Classifier: Environment :: GPU
Classifier: Intended Audience :: Science/Research
Classifier: Operating System :: Microsoft :: Windows
Classifier: Operating System :: MacOS
Classifier: Operating System :: POSIX :: Linux
Classifier: Programming Language :: Python :: 3 :: Only
Classifier: Programming Language :: Python :: 3.8
Classifier: Programming Language :: Python :: 3.9
Classifier: Programming Language :: Python :: 3.10
Classifier: Programming Language :: Python :: 3.11
Classifier: Topic :: Scientific/Engineering :: Artificial Intelligence
Requires-Python: >=3.8
License-File: LICENSE.md
Requires-Dist: pandas>=1.5.3
Requires-Dist: scipy>=1.10.1
Requires-Dist: torch>=2.0.0
Requires-Dist: torchaudio>=2.0.2
Requires-Dist: tqdm
Provides-Extra: interactive
Requires-Dist: jupyterlab; extra == "interactive"
Requires-Dist: scikit-learn; extra == "interactive"
Requires-Dist: seaborn; extra == "interactive"
Requires-Dist: mne; extra == "interactive"
Dynamic: author
Dynamic: author-email
Dynamic: classifier
Dynamic: description
Dynamic: description-content-type
Dynamic: home-page
Dynamic: keywords
Dynamic: license
Dynamic: license-file
Dynamic: project-url
Dynamic: provides-extra
Dynamic: requires-dist
Dynamic: requires-python
Dynamic: summary
